rpi_greenhouse-0.4.1.dist-info/WHEEL
rpi_greenhouse-0.4.1.dist-info/RECORD
rpi_greenhouse-0.4.1.dist-info/top_level.txt
rpi_greenhouse-0.4.1.dist-info/metadata.json
rpi_greenhouse-0.4.1.dist-info/METADATA
rpi_greenhouse-0.4.1.dist-info/DESCRIPTION.rst
rpi_greenhouse/greenhouse_database.py
rpi_greenhouse/greenhouse.py
rpi_greenhouse/greenhouse_indicator.py
rpi_greenhouse/__init__.py
