Metadata-Version: 2.0
Name: rpi-greenhouse
Version: 0.4.1
Summary: Simple interface to Raspberry Pi Plantpot Greenhouse add-on board
Home-page: https://github.com/bennuttall/rpi-greenhouse
Author: Ben Nuttall
Author-email: ben@raspberrypi.org
License: BSD
Keywords: raspberry pi,greenhouse,garden,plant,sensor
Platform: UNKNOWN
Classifier: Development Status :: 4 - Beta
Classifier: Programming Language :: Python :: 2
Classifier: Topic :: Home Automation
Classifier: Topic :: Education
Classifier: License :: OSI Approved :: BSD License
Requires-Dist: RPi.GPIO
